webargs_quixote/__init__.py
webargs_quixote/quixoteparser.py
webargs_quixote-0.1.1.dist-info/LICENSE
webargs_quixote-0.1.1.dist-info/WHEEL
webargs_quixote-0.1.1.dist-info/METADATA
webargs_quixote-0.1.1.dist-info/RECORD
